stream_manager_cli/__init__.py
stream_manager_cli/config.py
stream_manager_cli/core.py
stream_manager_cli/main.py
stream_manager_cli/player.py
stream_manager_cli/storage.py
stream_manager_cli/stream_checker.py
stream_manager_cli/ui.py
stream_manager_cli-0.2.0.dist-info/licenses/LICENSE
stream_manager_cli-0.2.0.dist-info/METADATA
stream_manager_cli-0.2.0.dist-info/WHEEL
stream_manager_cli-0.2.0.dist-info/entry_points.txt
stream_manager_cli-0.2.0.dist-info/top_level.txt
stream_manager_cli-0.2.0.dist-info/RECORD
